query_farm_airport_test_server/__init__.py
query_farm_airport_test_server/auth.py
query_farm_airport_test_server/collatz.sql
query_farm_airport_test_server/database_impl.py
query_farm_airport_test_server/py.typed
query_farm_airport_test_server/repro.py
query_farm_airport_test_server/repro2.py
query_farm_airport_test_server/server.py
query_farm_airport_test_server/utils.py
query_farm_airport_test_server-0.1.1.dist-info/METADATA
query_farm_airport_test_server-0.1.1.dist-info/WHEEL
query_farm_airport_test_server-0.1.1.dist-info/entry_points.txt
query_farm_airport_test_server-0.1.1.dist-info/RECORD
