Metadata-Version: 2.3
Name: query-farm-airport-test-server
Version: 0.1.1
Summary: An Apache Arrow Flight server that is used to test the Airport extension for DuckDB.
Project-URL: Repository, https://github.com/query-farm/python-airport-test-server.git
Project-URL: Issues, https://github.com/query-farm/python-airport-test-server/issues
Author-email: Rusty Conover <rusty@query.farm>
Requires-Python: >=3.12
Requires-Dist: duckdb>=1.3.1
Requires-Dist: pyarrow>=20.0.0
Requires-Dist: query-farm-duckdb-json-serialization>=0.1.1
Requires-Dist: query-farm-flight-server
